[
  {
    "row": 0,
    "column": 0,
    "value": 82
  },
  {
    "row": 0,
    "column": 1,
    "value": 91
  },
  {
    "row": 0,
    "column": 2,
    "value": 50
  },
  {
    "row": 0,
    "column": 3,
    "value": 69
  },
  {
    "row": 0,
    "column": 4,
    "value": 22
  },
  {
    "row": 0,
    "column": 5,
    "value": 41
  },
  {
    "row": 0,
    "column": 6,
    "value": 49
  },
  {
    "row": 0,
    "column": 7,
    "value": 25
  },
  {
    "row": 0,
    "column": 8,
    "value": 46
  },
  {
    "row": 0,
    "column": 9,
    "value": 61
  },
  {
    "row": 1,
    "column": 0,
    "value": 95
  },
  {
    "row": 1,
    "column": 1,
    "value": 54
  },
  {
    "row": 1,
    "column": 2,
    "value": 49
  },
  {
    "row": 1,
    "column": 3,
    "value": 63
  },
  {
    "row": 1,
    "column": 4,
    "value": 37
  },
  {
    "row": 1,
    "column": 5,
    "value": 12
  },
  {
    "row": 1,
    "column": 6,
    "value": 95
  },
  {
    "row": 1,
    "column": 7,
    "value": 46
  },
  {
    "row": 1,
    "column": 8,
    "value": 70
  },
  {
    "row": 1,
    "column": 9,
    "value": 35
  },
  {
    "row": 2,
    "column": 0,
    "value": 89
  },
  {
    "row": 2,
    "column": 1,
    "value": 41
  },
  {
    "row": 2,
    "column": 2,
    "value": 68
  },
  {
    "row": 2,
    "column": 3,
    "value": 84
  },
  {
    "row": 2,
    "column": 4,
    "value": 41
  },
  {
    "row": 2,
    "column": 5,
    "value": 90
  },
  {
    "row": 2,
    "column": 6,
    "value": 96
  },
  {
    "row": 2,
    "column": 7,
    "value": 72
  },
  {
    "row": 2,
    "column": 8,
    "value": 38
  },
  {
    "row": 2,
    "column": 9,
    "value": 29
  },
  {
    "row": 3,
    "column": 0,
    "value": 27
  },
  {
    "row": 3,
    "column": 1,
    "value": 18
  },
  {
    "row": 3,
    "column": 2,
    "value": 14
  },
  {
    "row": 3,
    "column": 3,
    "value": 90
  },
  {
    "row": 3,
    "column": 4,
    "value": 71
  },
  {
    "row": 3,
    "column": 5,
    "value": 17
  },
  {
    "row": 3,
    "column": 6,
    "value": 13
  },
  {
    "row": 3,
    "column": 7,
    "value": 27
  },
  {
    "row": 3,
    "column": 8,
    "value": 20
  },
  {
    "row": 3,
    "column": 9,
    "value": 94
  },
  {
    "row": 4,
    "column": 0,
    "value": 73
  },
  {
    "row": 4,
    "column": 1,
    "value": 97
  },
  {
    "row": 4,
    "column": 2,
    "value": 96
  },
  {
    "row": 4,
    "column": 3,
    "value": 14
  },
  {
    "row": 4,
    "column": 4,
    "value": 49
  },
  {
    "row": 4,
    "column": 5,
    "value": 100
  },
  {
    "row": 4,
    "column": 6,
    "value": 59
  },
  {
    "row": 4,
    "column": 7,
    "value": 77
  },
  {
    "row": 4,
    "column": 8,
    "value": 39
  },
  {
    "row": 4,
    "column": 9,
    "value": 50
  },
  {
    "row": 5,
    "column": 0,
    "value": 32
  },
  {
    "row": 5,
    "column": 1,
    "value": 19
  },
  {
    "row": 5,
    "column": 2,
    "value": 61
  },
  {
    "row": 5,
    "column": 3,
    "value": 38
  },
  {
    "row": 5,
    "column": 4,
    "value": 78
  },
  {
    "row": 5,
    "column": 5,
    "value": 71
  },
  {
    "row": 5,
    "column": 6,
    "value": 25
  },
  {
    "row": 5,
    "column": 7,
    "value": 36
  },
  {
    "row": 5,
    "column": 8,
    "value": 80
  },
  {
    "row": 5,
    "column": 9,
    "value": 67
  },
  {
    "row": 6,
    "column": 0,
    "value": 21
  },
  {
    "row": 6,
    "column": 1,
    "value": 16
  },
  {
    "row": 6,
    "column": 2,
    "value": 45
  },
  {
    "row": 6,
    "column": 3,
    "value": 58
  },
  {
    "row": 6,
    "column": 4,
    "value": 97
  },
  {
    "row": 6,
    "column": 5,
    "value": 28
  },
  {
    "row": 6,
    "column": 6,
    "value": 66
  },
  {
    "row": 6,
    "column": 7,
    "value": 95
  },
  {
    "row": 6,
    "column": 8,
    "value": 54
  },
  {
    "row": 6,
    "column": 9,
    "value": 15
  },
  {
    "row": 7,
    "column": 0,
    "value": 75
  },
  {
    "row": 7,
    "column": 1,
    "value": 46
  },
  {
    "row": 7,
    "column": 2,
    "value": 96
  },
  {
    "row": 7,
    "column": 3,
    "value": 91
  },
  {
    "row": 7,
    "column": 4,
    "value": 71
  },
  {
    "row": 7,
    "column": 5,
    "value": 84
  },
  {
    "row": 7,
    "column": 6,
    "value": 63
  },
  {
    "row": 7,
    "column": 7,
    "value": 49
  },
  {
    "row": 7,
    "column": 8,
    "value": 39
  },
  {
    "row": 7,
    "column": 9,
    "value": 81
  },
  {
    "row": 8,
    "column": 0,
    "value": 70
  },
  {
    "row": 8,
    "column": 1,
    "value": 45
  },
  {
    "row": 8,
    "column": 2,
    "value": 76
  },
  {
    "row": 8,
    "column": 3,
    "value": 82
  },
  {
    "row": 8,
    "column": 4,
    "value": 19
  },
  {
    "row": 8,
    "column": 5,
    "value": 65
  },
  {
    "row": 8,
    "column": 6,
    "value": 38
  },
  {
    "row": 8,
    "column": 7,
    "value": 99
  },
  {
    "row": 8,
    "column": 8,
    "value": 34
  },
  {
    "row": 8,
    "column": 9,
    "value": 55
  },
  {
    "row": 9,
    "column": 0,
    "value": 100
  },
  {
    "row": 9,
    "column": 1,
    "value": 45
  },
  {
    "row": 9,
    "column": 2,
    "value": 96
  },
  {
    "row": 9,
    "column": 3,
    "value": 62
  },
  {
    "row": 9,
    "column": 4,
    "value": 58
  },
  {
    "row": 9,
    "column": 5,
    "value": 27
  },
  {
    "row": 9,
    "column": 6,
    "value": 32
  },
  {
    "row": 9,
    "column": 7,
    "value": 35
  },
  {
    "row": 9,
    "column": 8,
    "value": 47
  },
  {
    "row": 9,
    "column": 9,
    "value": 63
  }
]